google_sheet_downloader.py
google_sheet_downloader-1.1.2.dist-info/METADATA
google_sheet_downloader-1.1.2.dist-info/WHEEL
google_sheet_downloader-1.1.2.dist-info/entry_points.txt
google_sheet_downloader-1.1.2.dist-info/top_level.txt
google_sheet_downloader-1.1.2.dist-info/RECORD
